{
  "name": "Enforce-Guardrails-Synapse",
  "properties": {
    "description": "This policy initiative is a group of policies that ensures Synapse workspaces is compliant per regulated Landing Zones.",
    "displayName": "Enforce recommended guardrails for Synapse workspaces",
    "metadata": {
      "alzCloudEnvironments": [
        "AzureCloud",
        "AzureChinaCloud",
        "AzureUSGovernment"
      ],
      "category": "Synapse",
      "source": "https://github.com/Azure/Enterprise-Scale/",
      "version": "1.1.0"
    },
    "parameters": {
      "synapseAllowedTenantIds": {
        "defaultValue": [
          "[subscription().tenantId]"
        ],
        "type": "array"
      },
      "synapseDataTraffic": {
        "allowedValues": [
          "Audit",
          "Deny",
          "Disabled"
        ],
        "defaultValue": "Deny",
        "type": "string"
      },
      "synapseDefender": {
        "allowedValues": [
          "DeployIfNotExists",
          "Disabled"
        ],
        "defaultValue": "DeployIfNotExists",
        "type": "string"
      },
      "synapseFwRules": {
        "allowedValues": [
          "Audit",
          "Disabled"
        ],
        "defaultValue": "Audit",
        "type": "string"
      },
      "synapseLocalAuth": {
        "allowedValues": [
          "Audit",
          "Deny",
          "Disabled"
        ],
        "defaultValue": "Deny",
        "type": "string"
      },
      "synapseManagedVnet": {
        "allowedValues": [
          "Audit",
          "Deny",
          "Disabled"
        ],
        "defaultValue": "Deny",
        "type": "string"
      },
      "synapseModifyLocalAuth": {
        "allowedValues": [
          "Modify",
          "Disabled"
        ],
        "defaultValue": "Modify",
        "type": "string"
      },
      "synapseModifyPublicNetworkAccess": {
        "allowedValues": [
          "Modify",
          "Disabled"
        ],
        "defaultValue": "Modify",
        "type": "string"
      },
      "synapseModifyTlsVersion": {
        "allowedValues": [
          "Modify",
          "Disabled"
        ],
        "defaultValue": "Modify",
        "type": "string"
      },
      "synapseTenants": {
        "allowedValues": [
          "Audit",
          "Deny",
          "Disabled"
        ],
        "defaultValue": "Deny",
        "type": "string"
      }
    },
    "policyDefinitions": [
      {
        "groupNames": [],
        "parameters": {
          "effect": {
            "value": "[parameters('synapseDefender')]"
          }
        },
        "policyDefinitionId": "/providers/Microsoft.Authorization/policyDefinitions/951c1558-50a5-4ca3-abb6-a93e3e2367a6",
        "policyDefinitionReferenceId": "Dine-Synapse-Defender"
      },
      {
        "groupNames": [],
        "parameters": {
          "effect": {
            "value": "[parameters('synapseModifyLocalAuth')]"
          }
        },
        "policyDefinitionId": "/providers/Microsoft.Authorization/policyDefinitions/c3624673-d2ff-48e0-b28c-5de1c6767c3c",
        "policyDefinitionReferenceId": "Modify-Synapse-Local-Auth"
      },
      {
        "groupNames": [],
        "parameters": {
          "effect": {
            "value": "[parameters('synapseFwRules')]"
          }
        },
        "policyDefinitionId": "/providers/Microsoft.Authorization/policyDefinitions/56fd377d-098c-4f02-8406-81eb055902b8",
        "policyDefinitionReferenceId": "Deny-Synapse-Fw-Rules"
      },
      {
        "groupNames": [],
        "parameters": {
          "allowedTenantIds": {
            "value": "[parameters('synapseAllowedTenantIds')]"
          },
          "effect": {
            "value": "[parameters('synapseTenants')]"
          }
        },
        "policyDefinitionId": "/providers/Microsoft.Authorization/policyDefinitions/3a003702-13d2-4679-941b-937e58c443f0",
        "policyDefinitionReferenceId": "Deny-Synapse-Tenant-Access"
      },
      {
        "groupNames": [],
        "parameters": {
          "effect": {
            "value": "[parameters('synapseDataTraffic')]"
          }
        },
        "policyDefinitionId": "/providers/Microsoft.Authorization/policyDefinitions/3484ce98-c0c5-4c83-994b-c5ac24785218",
        "policyDefinitionReferenceId": "Deny-Synapse-Data-Traffic"
      },
      {
        "groupNames": [],
        "parameters": {
          "effect": {
            "value": "[parameters('synapseManagedVnet')]"
          }
        },
        "policyDefinitionId": "/providers/Microsoft.Authorization/policyDefinitions/2d9dbfa3-927b-4cf0-9d0f-08747f971650",
        "policyDefinitionReferenceId": "Deny-Synapse-Managed-Vnet"
      },
      {
        "groupNames": [],
        "parameters": {
          "effect": {
            "value": "[parameters('synapseLocalAuth')]"
          }
        },
        "policyDefinitionId": "/providers/Microsoft.Authorization/policyDefinitions/2158ddbe-fefa-408e-b43f-d4faef8ff3b8",
        "policyDefinitionReferenceId": "Deny-Synapse-Local-Auth"
      },
      {
        "groupNames": [],
        "parameters": {
          "effect": {
            "value": "[parameters('synapseModifyTlsVersion')]"
          }
        },
        "policyDefinitionId": "/providers/Microsoft.Authorization/policyDefinitions/8b5c654c-fb07-471b-aa8f-15fea733f140",
        "policyDefinitionReferenceId": "Modify-Synapse-Tls-Version"
      },
      {
        "groupNames": [],
        "parameters": {
          "effect": {
            "value": "[parameters('synapseModifyPublicNetworkAccess')]"
          }
        },
        "policyDefinitionId": "/providers/Microsoft.Authorization/policyDefinitions/5c8cad01-ef30-4891-b230-652dadb4876a",
        "policyDefinitionReferenceId": "Modify-Synapse-Public-Network-Access"
      }
    ],
    "policyType": "Custom"
  },
  "type": "Microsoft.Authorization/policySetDefinitions"
}